peace_performance_python/__init__.py
peace_performance_python/_peace_performance.cpython-38-darwin.so
peace_performance_python/prelude.py
peace_performance_python/utils.py
peace_performance_python/_peace_performance/__init__.pyi
peace_performance_python/_peace_performance/beatmap.pyi
peace_performance_python/_peace_performance/common.pyi
peace_performance_python/_peace_performance/pp.pyi
peace_performance_python/_peace_performance/types.pyi
peace_performance_python/functions/__init__.py
peace_performance_python/functions/common.py
peace_performance_python/objects/__init__.py
peace_performance_python/objects/beatmap.py
peace_performance_python/objects/calculator.py
peace_performance_python/objects/pp_result.py
peace_performance_python/objects/utils.py
peace_performance_python-2.0.0.dist-info/LICENSE
peace_performance_python-2.0.0.dist-info/METADATA
peace_performance_python-2.0.0.dist-info/WHEEL
peace_performance_python-2.0.0.dist-info/top_level.txt
peace_performance_python-2.0.0.dist-info/RECORD
