Metadata-Version: 2.1
Name: peace-performance-python
Version: 2.0.0
Summary: Rust binding for python. To calculate star ratings and performance points for all osu! gamemodes, and quickly parse Beatmap into python objects.
Home-page: https://github.com/Pure-Peace/peace-performance-python
Author: Pure-Peace
Author-email: abner666666@foxmail.com
Maintainer: Pure-Peace
Maintainer-email: abner666666@foxmail.com
License: MIT License
Project-URL: repository, https://github.com/Pure-Peace/peace-performance-python
Keywords: rust,peace,osu,pp,beatmap,parse,rosu-pp,peace-performance
Classifier: License :: OSI Approved :: MIT License
Classifier: Development Status :: 4 - Beta
Classifier: Intended Audience :: Developers
Classifier: Operating System :: OS Independent
Classifier: Programming Language :: Python :: 3
Classifier: Programming Language :: Python :: 3.7
Classifier: Programming Language :: Python :: 3.8
Classifier: Programming Language :: Python :: 3.9
Classifier: Programming Language :: Python :: 3.10
Classifier: Programming Language :: Python :: Implementation :: CPython
Classifier: Programming Language :: Rust
Classifier: Operating System :: POSIX
Classifier: Operating System :: MacOS :: MacOS X
Classifier: Operating System :: Microsoft :: Windows
Requires-Python: >=3.7
Provides-Extra: test
License-File: LICENSE
